docs/ec2_solutions.ipynb
docs/requirements.txt
docs/source/conf.py
gbm_package-0.0.post2.dist-info/licenses/LICENSE
pygbm/__init__.py
pygbm/cli.py
pygbm/gbm_simulation.py
pygbm/version.py
gbm_package-0.0.post2.dist-info/METADATA
gbm_package-0.0.post2.dist-info/WHEEL
gbm_package-0.0.post2.dist-info/entry_points.txt
gbm_package-0.0.post2.dist-info/top_level.txt
gbm_package-0.0.post2.dist-info/RECORD
