Metadata-Version: 2.4
Name: gbm_package
Version: 0.0.post2
Summary: A Python package for simulation Geometric Brownian motions.
Author-email: Vahan <geghamyanvahan@gmail.com>, Boris <boris.bolliet@gmail.com>
License: MIT License
Project-URL: Documentation, https://your-readthedocs-url-here
Project-URL: Source, https://github.com/yourusername/companies_package
Project-URL: Issues, https://github.com/yourusername/companies_package/issues
Keywords: Brownian motion,finance,stochastic processes
Classifier: Development Status :: 4 - Beta
Classifier: Intended Audience :: Science/Research
Classifier: License :: OSI Approved :: MIT License
Classifier: Programming Language :: Python :: 3
Classifier: Topic :: Software Development :: Libraries
Requires-Python: >=3.9
License-File: LICENSE
Requires-Dist: numpy
Requires-Dist: pandas
Requires-Dist: argparse
Requires-Dist: datetime
Requires-Dist: importlib.resources
Dynamic: license-file
